{
  "timestamp": "02:17:24",
  "indices": [
    {
      "name": "NIFTY 50",
      "spot": 25482.5,
      "expiry": "2026-03-02",
      "lot": 65,
      "rows": [
        {
          "pair": "25450.0 / 25550.0",
          "ce_strike": 25450.0,
          "ce_ltp": 176.85,
          "ce_iv": 32.5,
          "ce_tv": 144.35,
          "ce_impv": 12.18,
          "pe_strike": 25550.0,
          "pe_ltp": 163.85,
          "pe_iv": 67.5,
          "pe_tv": 96.35,
          "pe_impv": 12.56,
          "diff": 48.0,
          "bias": "BUY PE",
          "lot": 65
        },
        {
          "pair": "25400.0 / 25600.0",
          "ce_strike": 25400.0,
          "ce_ltp": 209.7,
          "ce_iv": 82.5,
          "ce_tv": 127.2,
          "ce_impv": 12.45,
          "pe_strike": 25600.0,
          "pe_ltp": 190.75,
          "pe_iv": 117.5,
          "pe_tv": 73.25,
          "pe_impv": 12.43,
          "diff": 53.95,
          "bias": "BUY PE",
          "lot": 65
        },
        {
          "pair": "25350.0 / 25650.0",
          "ce_strike": 25350.0,
          "ce_ltp": 243.7,
          "ce_iv": 132.5,
          "ce_tv": 111.2,
          "ce_impv": 12.61,
          "pe_strike": 25650.0,
          "pe_ltp": 222.0,
          "pe_iv": 167.5,
          "pe_tv": 54.5,
          "pe_impv": 12.46,
          "diff": 56.7,
          "bias": "BUY PE",
          "lot": 65
        },
        {
          "pair": "25300.0 / 25700.0",
          "ce_strike": 25300.0,
          "ce_ltp": 280.85,
          "ce_iv": 182.5,
          "ce_tv": 98.35,
          "ce_impv": 12.85,
          "pe_strike": 25700.0,
          "pe_ltp": 255.0,
          "pe_iv": 217.5,
          "pe_tv": 37.5,
          "pe_impv": 12.41,
          "diff": 60.85,
          "bias": "BUY PE",
          "lot": 65
        },
        {
          "pair": "25250.0 / 25750.0",
          "ce_strike": 25250.0,
          "ce_ltp": 323.0,
          "ce_iv": 232.5,
          "ce_tv": 90.5,
          "ce_impv": 13.43,
          "pe_strike": 25750.0,
          "pe_ltp": 292.0,
          "pe_iv": 267.5,
          "pe_tv": 24.5,
          "pe_impv": 12.52,
          "diff": 66.0,
          "bias": "BUY PE",
          "lot": 65
        },
        {
          "pair": "25200.0 / 25800.0",
          "ce_strike": 25200.0,
          "ce_ltp": 363.15,
          "ce_iv": 282.5,
          "ce_tv": 80.65,
          "ce_impv": 13.64,
          "pe_strike": 25800.0,
          "pe_ltp": 332.0,
          "pe_iv": 317.5,
          "pe_tv": 14.5,
          "pe_impv": 12.75,
          "diff": 66.15,
          "bias": "BUY PE",
          "lot": 65
        }
      ]
    },
    {
      "name": "SENSEX",
      "spot": 82276.07,
      "expiry": "2026-02-26",
      "lot": 20,
      "rows": [
        {
          "pair": "82200.0 / 82400.0",
          "ce_strike": 82200.0,
          "ce_ltp": 314.15,
          "ce_iv": 76.07,
          "ce_tv": 238.08,
          "ce_impv": 17.46,
          "pe_strike": 82400.0,
          "pe_ltp": 307.5,
          "pe_iv": 123.93,
          "pe_tv": 183.57,
          "pe_impv": 16.52,
          "diff": 54.51,
          "bias": "BUY PE",
          "lot": 20
        },
        {
          "pair": "82100.0 / 82500.0",
          "ce_strike": 82100.0,
          "ce_ltp": 378.85,
          "ce_iv": 176.07,
          "ce_tv": 202.78,
          "ce_impv": 17.89,
          "pe_strike": 82500.0,
          "pe_ltp": 360.45,
          "pe_iv": 223.93,
          "pe_tv": 136.52,
          "pe_impv": 16.03,
          "diff": 66.26,
          "bias": "BUY PE",
          "lot": 20
        },
        {
          "pair": "82000.0 / 82600.0",
          "ce_strike": 82000.0,
          "ce_ltp": 445.55,
          "ce_iv": 276.07,
          "ce_tv": 169.48,
          "ce_impv": 18.1,
          "pe_strike": 82600.0,
          "pe_ltp": 426.2,
          "pe_iv": 323.93,
          "pe_tv": 102.27,
          "pe_impv": 15.99,
          "diff": 67.21,
          "bias": "BUY PE",
          "lot": 20
        },
        {
          "pair": "81900.0 / 82700.0",
          "ce_strike": 81900.0,
          "ce_ltp": 519.95,
          "ce_iv": 376.07,
          "ce_tv": 143.88,
          "ce_impv": 18.52,
          "pe_strike": 82700.0,
          "pe_ltp": 501.45,
          "pe_iv": 423.93,
          "pe_tv": 77.52,
          "pe_impv": 16.24,
          "diff": 66.36,
          "bias": "BUY PE",
          "lot": 20
        },
        {
          "pair": "81800.0 / 82800.0",
          "ce_strike": 81800.0,
          "ce_ltp": 597.15,
          "ce_iv": 476.07,
          "ce_tv": 121.08,
          "ce_impv": 18.84,
          "pe_strike": 82800.0,
          "pe_ltp": 575.3,
          "pe_iv": 523.93,
          "pe_tv": 51.37,
          "pe_impv": 15.95,
          "diff": 69.71,
          "bias": "BUY PE",
          "lot": 20
        },
        {
          "pair": "81700.0 / 82900.0",
          "ce_strike": 81700.0,
          "ce_ltp": 678.4,
          "ce_iv": 576.07,
          "ce_tv": 102.33,
          "ce_impv": 19.19,
          "pe_strike": 82900.0,
          "pe_ltp": 661.65,
          "pe_iv": 623.93,
          "pe_tv": 37.72,
          "pe_impv": 16.41,
          "diff": 64.61,
          "bias": "BUY PE",
          "lot": 20
        }
      ]
    },
    {
      "name": "BANKNIFTY",
      "spot": 61043.35,
      "expiry": "2026-03-30",
      "lot": 30,
      "rows": [
        {
          "pair": "60900.0 / 61100.0",
          "ce_strike": 60900.0,
          "ce_ltp": 1117.95,
          "ce_iv": 143.35,
          "ce_tv": 974.6,
          "ce_impv": 9.96,
          "pe_strike": 61100.0,
          "pe_ltp": 724.55,
          "pe_iv": 56.65,
          "pe_tv": 667.9,
          "pe_impv": 13.06,
          "diff": 306.7,
          "bias": "BUY PE",
          "lot": 30
        },
        {
          "pair": "60800.0 / 61200.0",
          "ce_strike": 60800.0,
          "ce_ltp": 1176.1,
          "ce_iv": 243.35,
          "ce_tv": 932.75,
          "ce_impv": 9.86,
          "pe_strike": 61200.0,
          "pe_ltp": 763.75,
          "pe_iv": 156.65,
          "pe_tv": 607.1,
          "pe_impv": 13.01,
          "diff": 325.65,
          "bias": "BUY PE",
          "lot": 30
        },
        {
          "pair": "60700.0 / 61300.0",
          "ce_strike": 60700.0,
          "ce_ltp": 1255.75,
          "ce_iv": 343.35,
          "ce_tv": 912.4,
          "ce_impv": 10.06,
          "pe_strike": 61300.0,
          "pe_ltp": 806.45,
          "pe_iv": 256.65,
          "pe_tv": 549.8,
          "pe_impv": 12.98,
          "diff": 362.6,
          "bias": "BUY PE",
          "lot": 30
        },
        {
          "pair": "60600.0 / 61400.0",
          "ce_strike": 60600.0,
          "ce_ltp": 1319.6,
          "ce_iv": 443.35,
          "ce_tv": 876.25,
          "ce_impv": 9.98,
          "pe_strike": 61400.0,
          "pe_ltp": 855.55,
          "pe_iv": 356.65,
          "pe_tv": 498.9,
          "pe_impv": 13.02,
          "diff": 377.35,
          "bias": "BUY PE",
          "lot": 30
        },
        {
          "pair": "60500.0 / 61500.0",
          "ce_strike": 60500.0,
          "ce_ltp": 1361.5,
          "ce_iv": 543.35,
          "ce_tv": 818.15,
          "ce_impv": 9.51,
          "pe_strike": 61500.0,
          "pe_ltp": 892.8,
          "pe_iv": 456.65,
          "pe_tv": 436.15,
          "pe_impv": 12.87,
          "diff": 382.0,
          "bias": "BUY PE",
          "lot": 30
        },
        {
          "pair": "60400.0 / 61600.0",
          "ce_strike": 60400.0,
          "ce_ltp": 1470.85,
          "ce_iv": 643.35,
          "ce_tv": 827.5,
          "ce_impv": 10.13,
          "pe_strike": 61600.0,
          "pe_ltp": 964.05,
          "pe_iv": 556.65,
          "pe_tv": 407.4,
          "pe_impv": 13.17,
          "diff": 420.1,
          "bias": "BUY PE",
          "lot": 30
        }
      ]
    },
    {
      "name": "MIDCAP",
      "spot": 13558.55,
      "expiry": "2026-03-30",
      "lot": 120,
      "rows": [
        {
          "pair": "13525.0 / 13575.0",
          "ce_strike": 13525.0,
          "ce_ltp": 336.0,
          "ce_iv": 33.55,
          "ce_tv": 302.45,
          "ce_impv": 15.59,
          "pe_strike": 13575.0,
          "pe_ltp": 250.05,
          "pe_iv": 16.45,
          "pe_tv": 233.6,
          "pe_impv": 18.56,
          "diff": 68.85,
          "bias": "BUY PE",
          "lot": 120
        },
        {
          "pair": "13500.0 / 13600.0",
          "ce_strike": 13500.0,
          "ce_ltp": 349.0,
          "ce_iv": 58.55,
          "ce_tv": 290.45,
          "ce_impv": 15.48,
          "pe_strike": 13600.0,
          "pe_ltp": 260.95,
          "pe_iv": 41.45,
          "pe_tv": 219.5,
          "pe_impv": 18.52,
          "diff": 70.95,
          "bias": "BUY PE",
          "lot": 120
        },
        {
          "pair": "13475.0 / 13625.0",
          "ce_strike": 13475.0,
          "ce_ltp": 362.4,
          "ce_iv": 83.55,
          "ce_tv": 278.85,
          "ce_impv": 15.36,
          "pe_strike": 13625.0,
          "pe_ltp": 277.3,
          "pe_iv": 66.45,
          "pe_tv": 210.85,
          "pe_impv": 18.81,
          "diff": 68.0,
          "bias": "BUY PE",
          "lot": 120
        },
        {
          "pair": "13450.0 / 13650.0",
          "ce_strike": 13450.0,
          "ce_ltp": 378.3,
          "ce_iv": 108.55,
          "ce_tv": 269.75,
          "ce_impv": 15.38,
          "pe_strike": 13650.0,
          "pe_ltp": 286.5,
          "pe_iv": 91.45,
          "pe_tv": 195.05,
          "pe_impv": 18.63,
          "diff": 74.7,
          "bias": "BUY PE",
          "lot": 120
        },
        {
          "pair": "13425.0 / 13675.0",
          "ce_strike": 13425.0,
          "ce_ltp": 397.6,
          "ce_iv": 133.55,
          "ce_tv": 264.05,
          "ce_impv": 15.61,
          "pe_strike": 13675.0,
          "pe_ltp": 300.5,
          "pe_iv": 116.45,
          "pe_tv": 184.05,
          "pe_impv": 18.72,
          "diff": 80.0,
          "bias": "BUY PE",
          "lot": 120
        },
        {
          "pair": "13400.0 / 13700.0",
          "ce_strike": 13400.0,
          "ce_ltp": 413.0,
          "ce_iv": 158.55,
          "ce_tv": 254.45,
          "ce_impv": 15.55,
          "pe_strike": 13700.0,
          "pe_ltp": 309.7,
          "pe_iv": 141.45,
          "pe_tv": 168.25,
          "pe_impv": 18.5,
          "diff": 86.2,
          "bias": "BUY PE",
          "lot": 120
        }
      ]
    }
  ]
}